{
  "project_info": {
    "project_number": "227646681291",
    "project_id": "mayan-828f9",
    "storage_bucket": "mayan-828f9.firebasestorage.app"
  },
  "client": [
    {
      "client_info": {
        "mobilesdk_app_id": "1:227646681291:android:31edb51b1e4e1d5f026b4e",
        "android_client_info": {
          "package_name": "com.example.mayan"
        }
      },
      "oauth_client": [],
      "api_key": [
        {
          "current_key": "AIzaSyD4O04_6edwreLwbiko4LW3DiY6VNnEvPA"
        }
      ],
      "services": {
        "appinvite_service": {
          "other_platform_oauth_client": []
        }
      }
    }
  ],
  "configuration_version": "1"
}